<?xml version="1.0" encoding="utf-8"?>
<!DOCTYPE hibernate-mapping PUBLIC "-//Hibernate/Hibernate Mapping DTD 3.0//EN"
"http://hibernate.sourceforge.net/hibernate-mapping-3.0.dtd">
<!-- 
    Mapping file autogenerated by MyEclipse Persistence Tools
-->
<hibernate-mapping>
    <class name="com.hibernate.model.Order" table="order" catalog="erestaurant">
        <id name="orderId" type="java.lang.Integer">
            <column name="order_id" />
            <generator class="identity" />
        </id>
        <many-to-one name="table" class="com.hibernate.model.Table" fetch="select">
            <column name="table_id" not-null="true" />
        </many-to-one>
        <many-to-one name="stuff" class="com.hibernate.model.Stuff" fetch="select">
            <column name="stuff_name" length="45" not-null="true" />
        </many-to-one>
        <property name="discount" type="java.lang.Double">
            <column name="discount" precision="22" scale="0" />
        </property>
        <property name="orderDate" type="java.sql.Timestamp">
            <column name="order_date" length="0" not-null="true" />
        </property>
        <set name="orderDetails" inverse="true">
            <key>
                <column name="order_id" not-null="true" />
            </key>
            <one-to-many class="com.hibernate.model.OrderDetail" />
        </set>
    </class>
</hibernate-mapping>
